
    <test name="AuthTestLDAPModule">
        <parameter name="testModule" value="ldap"/>
        <parameter name="testMode" value="module"/>
        <parameter name="instanceIndex" value="1"/>
        <groups>
            <run>
                <include name="@mode@"/>
            </run>
        </groups>
        <classes>
            <class name="com.sun.identity.qatest.authentication.ConfigUnconfig"/>
            <class name="com.sun.identity.qatest.authentication.AuthTest"/>
        </classes>
    </test>
    <test name="AuthTestLDAPService">
        <parameter name="testModule" value="ldap"/>
        <parameter name="testMode" value="service"/>
        <parameter name="instanceIndex" value="1"/>
        <groups>
            <run>
                <include name="@mode@"/>
            </run>
        </groups>
        <classes>
            <class name="com.sun.identity.qatest.authentication.AuthTest"/>
        </classes>
    </test>
    <test name="AuthTestLDAPAuthLevel">
        <parameter name="testModule" value="ldap"/>
        <parameter name="testMode" value="authlevel"/>
        <parameter name="instanceIndex" value="1"/>
        <groups>
            <run>
                <include name="@mode@"/>
            </run>
        </groups>
        <classes>
            <class name="com.sun.identity.qatest.authentication.AuthTest"/>
        </classes>
    </test>
    <test name="AuthTestLDAPRealm">
        <parameter name="testModule" value="ldap"/>
        <parameter name="testMode" value="realm"/>
        <parameter name="instanceIndex" value="1"/>
        <groups>
            <run>
                <include name="@mode@"/>
            </run>
        </groups>
        <classes>
            <class name="com.sun.identity.qatest.authentication.AuthTest"/>
        </classes>
    </test>
    <test name="AuthTestADUser">
        <parameter name="testModule" value="ad"/>
        <parameter name="testMode" value="user"/>
        <parameter name="instanceIndex" value="1"/>
        <groups>
            <run>
                <include name="@mode@"/>
            </run>
        </groups>
        <classes>
            <class name="com.sun.identity.qatest.authentication.AuthTest"/>
        </classes>
    </test>
    <test name="AuthTestADModule">
        <parameter name="testModule" value="ad"/>
        <parameter name="testMode" value="module"/>
        <parameter name="instanceIndex" value="1"/>
        <groups>
            <run>
                <include name="@mode@"/>
            </run>
        </groups>
        <classes>
            <class name="com.sun.identity.qatest.authentication.AuthTest"/>
        </classes>
    </test>
    <test name="AuthTestADService">
        <parameter name="testModule" value="ad"/>
        <parameter name="testMode" value="service"/>
        <parameter name="instanceIndex" value="1"/>
        <groups>
            <run>
                <include name="@mode@"/>
            </run>
        </groups>
        <classes>
            <class name="com.sun.identity.qatest.authentication.AuthTest"/>
        </classes>
    </test>
    <test name="AuthTestADAuthLevel">
        <parameter name="testModule" value="ad"/>
        <parameter name="testMode" value="authlevel"/>
        <parameter name="instanceIndex" value="1"/>
        <groups>
            <run>
                <include name="@mode@"/>
            </run>
        </groups>
        <classes>
            <class name="com.sun.identity.qatest.authentication.AuthTest"/>
        </classes>
    </test>
    <test name="AuthTestADRealm">
        <parameter name="testModule" value="ad"/>
        <parameter name="testMode" value="realm"/>
        <parameter name="instanceIndex" value="1"/>
        <groups>
            <run>
                <include name="@mode@"/>
            </run>
        </groups>
        <classes>
            <class name="com.sun.identity.qatest.authentication.AuthTest"/>
        </classes>
    </test>
   <test name="AuthTestLDAPUser">
        <parameter name="testModule" value="ldap"/>
        <parameter name="testMode" value="user"/>
        <parameter name="instanceIndex" value="1"/>
        <groups>
            <run>
                <include name="@mode@"/>
            </run>
        </groups>
        <classes>
            <class name="com.sun.identity.qatest.authentication.AuthTest"/>
        </classes>
   </test>
