
    <test name="AuthTestADUser">
        <parameter name="testModule" value="ad"/>
        <parameter name="testMode" value="user"/>
        <parameter name="instanceIndex" value="1"/>
        <groups>
            <run>
                <include name="@mode@"/>
            </run>
        </groups>
        <classes>
            <class name="com.sun.identity.qatest.authentication.AuthTest"/>
        </classes>
    </test>
    <test name="AuthTestADModule">
        <parameter name="testModule" value="ad"/>
        <parameter name="testMode" value="module"/>
        <parameter name="instanceIndex" value="1"/>
        <groups>
            <run>
                <include name="@mode@"/>
            </run>
        </groups>
        <classes>
            <class name="com.sun.identity.qatest.authentication.AuthTest"/>
        </classes>
    </test>
    <test name="AuthTestADService">
        <parameter name="testModule" value="ad"/>
        <parameter name="testMode" value="service"/>
        <parameter name="instanceIndex" value="1"/>
        <groups>
            <run>
                <include name="@mode@"/>
            </run>
        </groups>
        <classes>
            <class name="com.sun.identity.qatest.authentication.AuthTest"/>
        </classes>
    </test>
    <test name="AuthTestADAuthLevel">
        <parameter name="testModule" value="ad"/>
        <parameter name="testMode" value="authlevel"/>
        <parameter name="instanceIndex" value="1"/>
        <groups>
            <run>
                <include name="@mode@"/>
            </run>
        </groups>
        <classes>
            <class name="com.sun.identity.qatest.authentication.AuthTest"/>
        </classes>
    </test>
    <test name="AuthTestADRealm">
        <parameter name="testModule" value="ad"/>
        <parameter name="testMode" value="realm"/>
        <parameter name="instanceIndex" value="1"/>
        <groups>
            <run>
                <include name="@mode@"/>
            </run>
        </groups>
        <classes>
            <class name="com.sun.identity.qatest.authentication.AuthTest"/>
        </classes>
    </test>
    <test name="AuthTestNTUser">
        <parameter name="testModule" value="nt"/>
        <parameter name="testMode" value="user"/>
        <parameter name="instanceIndex" value="1"/>
        <groups>
            <run>
                <include name="@mode@"/>
            </run>
        </groups>
        <classes>
            <class name="com.sun.identity.qatest.authentication.AuthTest"/>
        </classes>
    </test>
    <test name="AuthTestNTModule">
        <parameter name="testModule" value="nt"/>
        <parameter name="testMode" value="module"/>
        <parameter name="instanceIndex" value="1"/>
        <groups>
            <run>
                <include name="@mode@"/>
            </run>
        </groups>
        <classes>
            <class name="com.sun.identity.qatest.authentication.AuthTest"/>
        </classes>
    </test>
    <test name="AuthTestNTService">
        <parameter name="testModule" value="nt"/>
        <parameter name="testMode" value="service"/>
        <parameter name="instanceIndex" value="1"/>
        <groups>
            <run>
                <include name="@mode@"/>
            </run>
        </groups>
        <classes>
            <class name="com.sun.identity.qatest.authentication.AuthTest"/>
        </classes>
    </test>
    <test name="AuthTestNTAuthLevel">
        <parameter name="testModule" value="nt"/>
        <parameter name="testMode" value="authlevel"/>
        <parameter name="instanceIndex" value="1"/>
        <groups>
            <run>
                <include name="@mode@"/>
            </run>
        </groups>
        <classes>
            <class name="com.sun.identity.qatest.authentication.AuthTest"/>
        </classes>
    </test>
    <test name="AuthTestNTRealm">
        <parameter name="testModule" value="nt"/>
        <parameter name="testMode" value="realm"/>
        <parameter name="instanceIndex" value="1"/>
        <groups>
            <run>
                <include name="@mode@"/>
            </run>
        </groups>
        <classes>
            <class name="com.sun.identity.qatest.authentication.AuthTest"/>
        </classes>
    </test>
    <test name="AuthTestJDBCUser">
        <parameter name="testModule" value="jdbc"/>
        <parameter name="testMode" value="user"/>
        <parameter name="instanceIndex" value="1"/>
        <groups>
            <run>
                <include name="@mode@"/>
            </run>
        </groups>
        <classes>
            <class name="com.sun.identity.qatest.authentication.AuthTest"/>
        </classes>
    </test>
    <test name="AuthTestJDBCModule">
        <parameter name="testModule" value="jdbc"/>
        <parameter name="testMode" value="module"/>
        <parameter name="instanceIndex" value="1"/>
        <groups>
            <run>
                <include name="@mode@"/>
            </run>
        </groups>
        <classes>
            <class name="com.sun.identity.qatest.authentication.AuthTest"/>
        </classes>
    </test>
    <test name="AuthTestJDBCService">
        <parameter name="testModule" value="jdbc"/>
        <parameter name="testMode" value="service"/>
        <parameter name="instanceIndex" value="1"/>
        <groups>
            <run>
                <include name="@mode@"/>
            </run>
        </groups>
        <classes>
            <class name="com.sun.identity.qatest.authentication.AuthTest"/>
        </classes>
    </test>
    <test name="AuthTestJDBCAuthLevel">
        <parameter name="testModule" value="jdbc"/>
        <parameter name="testMode" value="authlevel"/>
        <parameter name="instanceIndex" value="1"/>
        <groups>
            <run>
                <include name="@mode@"/>
            </run>
        </groups>
        <classes>
            <class name="com.sun.identity.qatest.authentication.AuthTest"/>
        </classes>
    </test>
    <test name="AuthTestJDBCRealm">
        <parameter name="testModule" value="jdbc"/>
        <parameter name="testMode" value="realm"/>
        <parameter name="instanceIndex" value="1"/>
        <groups>
            <run>
                <include name="@mode@"/>
            </run>
        </groups>
        <classes>
            <class name="com.sun.identity.qatest.authentication.AuthTest"/>
        </classes>
    </test>
    <test name="AuthTestRadiusUser">
        <parameter name="testModule" value="radius"/>
        <parameter name="testMode" value="user"/>
        <parameter name="instanceIndex" value="1"/>
        <groups>
            <run>
                <include name="@mode@"/>
            </run>
        </groups>
        <classes>
            <class name="com.sun.identity.qatest.authentication.AuthTest"/>
        </classes>
    </test>
    <test name="AuthTestRadiusModule">
        <parameter name="testModule" value="radius"/>
        <parameter name="testMode" value="module"/>
        <parameter name="instanceIndex" value="1"/>
        <groups>
            <run>
                <include name="@mode@"/>
            </run>
        </groups>
        <classes>
            <class name="com.sun.identity.qatest.authentication.AuthTest"/>
        </classes>
    </test>
    <test name="AuthTestRadiusService">
        <parameter name="testModule" value="radius"/>
        <parameter name="testMode" value="service"/>
        <parameter name="instanceIndex" value="1"/>
        <groups>
            <run>
                <include name="@mode@"/>
            </run>
        </groups>
        <classes>
            <class name="com.sun.identity.qatest.authentication.AuthTest"/>
        </classes>
    </test>
    <test name="AuthTestRadiusAuthLevel">
        <parameter name="testModule" value="radius"/>
        <parameter name="testMode" value="authlevel"/>
        <parameter name="instanceIndex" value="1"/>
        <groups>
            <run>
                <include name="@mode@"/>
            </run>
        </groups>
        <classes>
            <class name="com.sun.identity.qatest.authentication.AuthTest"/>
        </classes>
    </test>
    <test name="AuthTestRadiusRealm">
        <parameter name="testModule" value="radius"/>
        <parameter name="testMode" value="realm"/>
        <parameter name="instanceIndex" value="1"/>
        <groups>
            <run>
                <include name="@mode@"/>
            </run>
        </groups>
        <classes>
            <class name="com.sun.identity.qatest.authentication.AuthTest"/>
        </classes>
    </test>
    <test name="AuthTestUnixUser">
        <parameter name="testModule" value="unix"/>
        <parameter name="testMode" value="user"/>
        <parameter name="instanceIndex" value="1"/>
        <groups>
            <run>
                <include name="@mode@"/>
            </run>
        </groups>
        <classes>
            <class name="com.sun.identity.qatest.authentication.AuthTest"/>
        </classes>
    </test>
    <test name="AuthTestUnixModule">
        <parameter name="testModule" value="unix"/>
        <parameter name="testMode" value="module"/>
        <parameter name="instanceIndex" value="1"/>
        <groups>
            <run>
                <include name="@mode@"/>
            </run>
        </groups>
        <classes>
            <class name="com.sun.identity.qatest.authentication.AuthTest"/>
        </classes>
    </test>
    <test name="AuthTestUnixService">
        <parameter name="testModule" value="unix"/>
        <parameter name="testMode" value="service"/>
        <parameter name="instanceIndex" value="1"/>
        <groups>
            <run>
                <include name="@mode@"/>
            </run>
        </groups>
        <classes>
            <class name="com.sun.identity.qatest.authentication.AuthTest"/>
        </classes>
    </test>
    <test name="AuthTestUnixAuthLevel">
        <parameter name="testModule" value="unix"/>
        <parameter name="testMode" value="authlevel"/>
        <parameter name="instanceIndex" value="1"/>
        <groups>
            <run>
                <include name="@mode@"/>
            </run>
        </groups>
        <classes>
            <class name="com.sun.identity.qatest.authentication.AuthTest"/>
        </classes>
    </test>
    <test name="AuthTestUnixRealm">
        <parameter name="testModule" value="unix"/>
        <parameter name="testMode" value="realm"/>
        <parameter name="instanceIndex" value="1"/>
        <groups>
            <run>
                <include name="@mode@"/>
            </run>
        </groups>
        <classes>
            <class name="com.sun.identity.qatest.authentication.AuthTest"/>
        </classes>
    </test>
    <test name="ChainTestRequired">
        <parameter name="testChainName" value="chain1"/>
        <parameter name="testRealm" value="/"/>
        <groups>
            <run>
                <include name="@mode@"/>
            </run>
        </groups>
        <classes>
            <class name="com.sun.identity.qatest.authentication.ChainTest"/>
        </classes>
    </test>
    <test name="ChainTestRequisite">
        <parameter name="testChainName" value="chain2"/>
        <parameter name="testRealm" value="/"/>
        <groups>
            <run>
                <include name="@mode@"/>
            </run>
        </groups>
        <classes>
            <class name="com.sun.identity.qatest.authentication.ChainTest"/>
        </classes>
    </test>
    <test name="ChainTestOneUsernamePassword">
        <parameter name="testChainName" value="chain3"/>
        <parameter name="testRealm" value="/"/>
        <groups>
            <run>
                <include name="@mode@"/>
            </run>
        </groups>
        <classes>
            <class name="com.sun.identity.qatest.authentication.ChainTest"/>
        </classes>
    </test>
    <test name="ChainTestOptional">
        <parameter name="testChainName" value="chain4"/>
        <parameter name="testRealm" value="/"/>
        <groups>
            <run>
                <include name="@mode@"/>
            </run>
        </groups>
        <classes>
            <class name="com.sun.identity.qatest.authentication.ChainTest"/>
        </classes>
    </test>
    <test name="ChainTestOptionalAuthFails">
        <parameter name="testChainName" value="chain5"/>
        <parameter name="testRealm" value="/"/>
        <groups>
            <run>
                <include name="@mode@"/>
            </run>
        </groups>
        <classes>
            <class name="com.sun.identity.qatest.authentication.ChainTest"/>
        </classes>
    </test>
    <test name="ChainTestSufficient">
        <parameter name="testChainName" value="chain6"/>
        <parameter name="testRealm" value="/"/>
        <groups>
            <run>
                <include name="@mode@"/>
            </run>
        </groups>
        <classes>
            <class name="com.sun.identity.qatest.authentication.ChainTest"/>
        </classes>
    </test>
    <test name="ChainTestSufficientFails">
        <parameter name="testChainName" value="chain7"/>
        <parameter name="testRealm" value="/"/>
        <groups>
            <run>
                <include name="@mode@"/>
            </run>
        </groups>
        <classes>
            <class name="com.sun.identity.qatest.authentication.ChainTest"/>
        </classes>
    </test>
    <test name="RedirectTestNTRootRealm">
        <parameter name="testModule" value="nt"/>
        <parameter name="testRealm" value="/"/>
        <parameter name="instanceIndex" value="1"/>
        <groups>
            <run>
                <include name="@mode@"/>
            </run>
        </groups>
        <classes>
            <class name="com.sun.identity.qatest.authentication.RedirectTest"/>
        </classes>
    </test>
     <test name="RedirectTestNTSubRealm">
        <parameter name="testModule" value="nt"/>
        <parameter name="testRealm" value="gotontrealm"/>
        <parameter name="instanceIndex" value="1"/>
        <groups>
            <run>
                <include name="@mode@"/>
            </run>
        </groups>
        <classes>
            <class name="com.sun.identity.qatest.authentication.RedirectTest"/>
        </classes>
    </test>
    <test name="RedirectTestJDBCRootRealm">
        <parameter name="testModule" value="jdbc"/>
        <parameter name="testRealm" value="/"/>
        <parameter name="instanceIndex" value="1"/>
        <groups>
            <run>
                <include name="@mode@"/>
            </run>
        </groups>
        <classes>
            <class name="com.sun.identity.qatest.authentication.RedirectTest"/>
        </classes>
    </test>
     <test name="RedirectTestJDBCSubRealm">
        <parameter name="testModule" value="jdbc"/>
        <parameter name="testRealm" value="gotojdbcrealm"/>
        <parameter name="instanceIndex" value="1"/>
        <groups>
            <run>
                <include name="@mode@"/>
            </run>
        </groups>
        <classes>
            <class name="com.sun.identity.qatest.authentication.RedirectTest"/>
        </classes>
    </test>
    <test name="RedirectTestADRootRealm">
        <parameter name="testModule" value="ad"/>
        <parameter name="testRealm" value="/"/>
        <parameter name="instanceIndex" value="1"/>
        <groups>
            <run>
                <include name="@mode@"/>
            </run>
        </groups>
        <classes>
            <class name="com.sun.identity.qatest.authentication.RedirectTest"/>
        </classes>
    </test>
     <test name="RedirectTestADSubRealm">
        <parameter name="testModule" value="ad"/>
        <parameter name="testRealm" value="gotoadrealm"/>
        <parameter name="instanceIndex" value="1"/>
        <groups>
            <run>
                <include name="@mode@"/>
            </run>
        </groups>
        <classes>
            <class name="com.sun.identity.qatest.authentication.RedirectTest"/>
        </classes>
    </test>
    <test name="RedirectTestRadiusRootRealm">
        <parameter name="testModule" value="radius"/>
        <parameter name="testRealm" value="/"/>
        <parameter name="instanceIndex" value="1"/>
        <groups>
            <run>
                <include name="@mode@"/>
            </run>
        </groups>
        <classes>
            <class name="com.sun.identity.qatest.authentication.RedirectTest"/>
        </classes>
    </test>
    <test name="RedirectTestRadiusSubRealm">
        <parameter name="testModule" value="radius"/>
        <parameter name="testRealm" value="gotoradiusrealm"/>
        <parameter name="instanceIndex" value="1"/>
        <groups>
            <run>
                <include name="@mode@"/>
            </run>
        </groups>
        <classes>
            <class name="com.sun.identity.qatest.authentication.RedirectTest"/>
        </classes>
    </test>
    <test name="RedirectTestUnixRootRealm">
        <parameter name="testModule" value="unix"/>
        <parameter name="testRealm" value="/"/>
        <parameter name="instanceIndex" value="1"/>
        <groups>
            <run>
                <include name="@mode@"/>
            </run>
        </groups>
        <classes>
            <class name="com.sun.identity.qatest.authentication.RedirectTest"/>
        </classes>
    </test>
    <test name="RedirectTestUnixSubRealm">
        <parameter name="testModule" value="unix"/>
        <parameter name="testRealm" value="gotounixrealm"/>
        <parameter name="instanceIndex" value="1"/>
        <groups>
            <run>
                <include name="@mode@"/>
            </run>
        </groups>
        <classes>
            <class name="com.sun.identity.qatest.authentication.RedirectTest"/>
        </classes>
    </test>
    <test name="AccountLockoutTest">
        <parameter name="testRealm" value="/"/>
        <groups>
            <run>
                <include name="@mode@"/>
            </run>
        </groups>
        <classes>
            <class name="com.sun.identity.qatest.authentication.AccountLockoutTest"/>
        </classes>
    </test>
    <test name="ProfileAttributesDynamicTest">
        <parameter name="testProfile" value="dynamic"/>
        <parameter name="instanceIndex" value="1"/>
        <groups>
            <run>
                <include name="@mode@"/>
            </run>
        </groups>
        <classes>
            <class name="com.sun.identity.qatest.authentication.ProfileAttributesTest"/>
        </classes>
    </test>
    <test name="ProfileAttributesIgnoredTest">
        <parameter name="testProfile" value="ignored"/>
        <parameter name="instanceIndex" value="1"/>
        <groups>
            <run>
                <include name="@mode@"/>
            </run>
        </groups>
        <classes>
            <class name="com.sun.identity.qatest.authentication.ProfileAttributesTest"/>
        </classes>
    </test>
    <test name="SessionUpgradeTest">
        <parameter name="forceAuth" value="false"/>
        <parameter name="testRealm" value="/"/>
        <parameter name="testMode" value="module"/>
        <parameter name="useDifferentModules" value="true"/>
        <parameter name="upgradeTestType" value="extended"/>
        <groups>
            <run>
                <include name="@mode@"/>
            </run>
        </groups>
        <classes>
            <class name="com.sun.identity.qatest.authentication.SessionUpgrade"/>
        </classes>
    </test>
    <test name="SessionUpgradeIgnoreTest">
        <parameter name="forceAuth" value="false"/>
        <parameter name="testRealm" value="/"/>
        <parameter name="testMode" value="module"/>
        <parameter name="useDifferentModules" value="true"/>
        <parameter name="upgradeTestType" value="ignore"/>
        <groups>
            <run>
                <include name="@mode@"/>
            </run>
        </groups>
        <classes>
            <class name="com.sun.identity.qatest.authentication.SessionUpgrade"/>
        </classes>
    </test>
    <test name="SessionUpgradeTestForceAuth">
        <parameter name="forceAuth" value="true"/>
        <parameter name="testRealm" value="/"/>   
        <parameter name="testMode" value="module"/>
        <parameter name="useDifferentModules" value="true"/>
        <parameter name="upgradeTestType" value="extended"/>
        <groups>
            <run>
                <include name="@mode@"/>
            </run>
        </groups>
        <classes>
            <class name="com.sun.identity.qatest.authentication.SessionUpgrade"/>
        </classes>
    </test>
    <test name="SessionUpgradeTestIgnoreforceAuth">
        <parameter name="forceAuth" value="true"/>
        <parameter name="testRealm" value="/"/>   
        <parameter name="testMode" value="module"/>
        <parameter name="useDifferentModules" value="true"/>
        <parameter name="upgradeTestType" value="ignore"/>
        <groups>
            <run>
                <include name="@mode@"/>
            </run>
        </groups>
        <classes>
            <class name="com.sun.identity.qatest.authentication.SessionUpgrade"/>
        </classes>
    </test>
    <test name="SessionUpgradeTestSubRealm">
        <parameter name="forceAuth" value="false"/>
        <parameter name="testRealm" value="upgradeRealm5"/>
        <parameter name="testMode" value="module"/>
        <parameter name="useDifferentModules" value="true"/>
        <parameter name="upgradeTestType" value="extended"/>
        <groups>
            <run>
                <include name="@mode@"/>
            </run>
        </groups>
        <classes>
            <class name="com.sun.identity.qatest.authentication.SessionUpgrade"/>
        </classes>
   </test>
   <test name="SessionUpgradeTestIgnoreSubRealm">
        <parameter name="forceAuth" value="false"/>
        <parameter name="testRealm" value="upgradeRealm6"/>
        <parameter name="testMode" value="module"/>
        <parameter name="useDifferentModules" value="true"/>
        <parameter name="upgradeTestType" value="ignore"/>
        <groups>
            <run>
                <include name="@mode@"/>
            </run>
        </groups>
        <classes>
            <class name="com.sun.identity.qatest.authentication.SessionUpgrade"/>
        </classes>
    </test>
    <test name="SessionUpgradeTestForceAuthSubRealm">
        <parameter name="forceAuth" value="true"/>
        <parameter name="testRealm" value="upgradeRealm7"/>
        <parameter name="testMode" value="module"/>
        <parameter name="useDifferentModules" value="true"/>
        <parameter name="upgradeTestType" value="extended"/>
        <groups>
            <run>
                <include name="@mode@"/>
            </run>
        </groups>
        <classes>
            <class name="com.sun.identity.qatest.authentication.SessionUpgrade"/>
        </classes>
    </test>
    <test name="SessionUpgradeTestIgnoreforceAuthSubRealm">
        <parameter name="forceAuth" value="true"/>
        <parameter name="testRealm" value="upgradeRealm8"/>
        <parameter name="testMode" value="module"/>
        <parameter name="useDifferentModules" value="true"/>
        <parameter name="upgradeTestType" value="ignore"/>
        <groups>
            <run>
                <include name="@mode@"/>
            </run>
        </groups>
        <classes>
            <class name="com.sun.identity.qatest.authentication.SessionUpgrade"/>
        </classes>
    </test>
    <test name="SessionUpgradeLevelTest">
        <parameter name="forceAuth" value="false"/>
        <parameter name="testRealm" value="/"/>
        <parameter name="testMode" value="level"/>
        <parameter name="useDifferentModules" value="true"/>
        <parameter name="upgradeTestType" value="extended"/>
        <groups>
            <run>
                <include name="@mode@"/>
            </run>
        </groups>
        <classes>
            <class name="com.sun.identity.qatest.authentication.SessionUpgrade"/>
        </classes>
    </test>
    <test name="SessionUpgradeLevelIgnoreTest">
        <parameter name="forceAuth" value="false"/>
        <parameter name="testRealm" value="/"/>
        <parameter name="testMode" value="level"/>
        <parameter name="useDifferentModules" value="true"/>
        <parameter name="upgradeTestType" value="ignore"/>
        <groups>
            <run>
                <include name="@mode@"/>
            </run>
        </groups>
        <classes>
            <class name="com.sun.identity.qatest.authentication.SessionUpgrade"/>
        </classes>
    </test>
    <test name="SessionUpgradeLevelTestForceAuth">
        <parameter name="forceAuth" value="true"/>
        <parameter name="testRealm" value="/"/>
        <parameter name="testMode" value="level"/>
        <parameter name="useDifferentModules" value="true"/>
        <parameter name="upgradeTestType" value="extended"/>
        <groups>
            <run>
                <include name="@mode@"/>
            </run>
        </groups>
        <classes>
            <class name="com.sun.identity.qatest.authentication.SessionUpgrade"/>
        </classes>
    </test>
    <test name="SessionUpgradeLevelIgnoreTestForceAuth">
        <parameter name="forceAuth" value="true"/>
        <parameter name="testRealm" value="/"/>
        <parameter name="testMode" value="level"/>
        <parameter name="useDifferentModules" value="true"/>
        <parameter name="upgradeTestType" value="ignore"/>
        <groups>
            <run>
                <include name="@mode@"/>
            </run>
        </groups>
        <classes>
            <class name="com.sun.identity.qatest.authentication.SessionUpgrade"/>
        </classes>
    </test>
  <test name="SessionUpgradeLevelTestSubRealm">
        <parameter name="forceAuth" value="false"/>
        <parameter name="testRealm" value="upgradeRealm9"/>
        <parameter name="testMode" value="level"/>
        <parameter name="useDifferentModules" value="true"/>
        <parameter name="upgradeTestType" value="extended"/>
        <groups>
            <run>
                <include name="@mode@"/>
            </run>
        </groups>
        <classes>
            <class name="com.sun.identity.qatest.authentication.SessionUpgrade"/>
        </classes>
    </test>
   <test name="SessionUpgradeLevelIgnoreTestSubRealm">
        <parameter name="forceAuth" value="false"/>
        <parameter name="testRealm" value="upgradeRealm10"/>
        <parameter name="testMode" value="level"/>
        <parameter name="useDifferentModules" value="true"/>
        <parameter name="upgradeTestType" value="ignore"/>
        <groups>
            <run>
                <include name="@mode@"/>
            </run>
        </groups>
        <classes>
            <class name="com.sun.identity.qatest.authentication.SessionUpgrade"/>
        </classes>
    </test>
    <test name="SessionUpgradeLevelTestForceAuthSubRealm">
        <parameter name="forceAuth" value="true"/>
        <parameter name="testRealm" value="upgradeRealm11"/>
        <parameter name="testMode" value="level"/>
        <parameter name="useDifferentModules" value="true"/>
        <parameter name="upgradeTestType" value="extended"/>
        <groups>
            <run>
                <include name="@mode@"/>
            </run>
        </groups>
        <classes>
            <class name="com.sun.identity.qatest.authentication.SessionUpgrade"/>
        </classes>
    </test>
    <test name="SessionUpgradeLevelTestIgnoreforceAuthSubRealm">
        <parameter name="forceAuth" value="true"/>
        <parameter name="testRealm" value="upgradeRealm12"/>
        <parameter name="testMode" value="level"/>
        <parameter name="useDifferentModules" value="true"/>
        <parameter name="upgradeTestType" value="ignore"/>
        <groups>
            <run>
                <include name="@mode@"/>
            </run>
        </groups>
        <classes>
            <class name="com.sun.identity.qatest.authentication.SessionUpgrade"/>
        </classes>
    </test>
    <test name="SessionUpgradeTestSameModule">
        <parameter name="forceAuth" value="false"/>
        <parameter name="testRealm" value="/"/>
        <parameter name="testMode" value="module"/>
        <parameter name="useDifferentModules" value="false"/>
        <parameter name="upgradeTestType" value="extended"/>
        <groups>
            <run>
                <include name="@mode@"/>
            </run>
        </groups>
        <classes>
            <class name="com.sun.identity.qatest.authentication.SessionUpgrade"/>
        </classes>
    </test>
    <test name="SessionUpgradeTestForceAuthSameModule">
        <parameter name="forceAuth" value="true"/>
        <parameter name="testRealm" value="/"/>
        <parameter name="testMode" value="module"/>
        <parameter name="useDifferentModules" value="false"/>
        <parameter name="upgradeTestType" value="extended"/>
        <groups>
            <run>
                <include name="@mode@"/>
            </run>
        </groups>
        <classes>
            <class name="com.sun.identity.qatest.authentication.SessionUpgrade"/>
        </classes>
    </test>
   <test name="SessionUpgradeTestSubRealmSameModule">
        <parameter name="forceAuth" value="false"/>
        <parameter name="testRealm" value="upgradeRealm13"/>
        <parameter name="testMode" value="module"/>
        <parameter name="useDifferentModules" value="false"/>
        <parameter name="upgradeTestType" value="extended"/>
        <groups>
            <run>
                <include name="@mode@"/>
            </run>
        </groups>
        <classes>
            <class name="com.sun.identity.qatest.authentication.SessionUpgrade"/>
        </classes>
    </test>
    <test name="SessionUpgradeTestForceAuthSubRealmSameModule">
        <parameter name="forceAuth" value="true"/>
        <parameter name="testRealm" value="upgradeRealm14"/>
        <parameter name="testMode" value="module"/>
        <parameter name="useDifferentModules" value="false"/>
        <parameter name="upgradeTestType" value="extended"/>
        <groups>
            <run>
                <include name="@mode@"/>
            </run>
        </groups>
        <classes>
            <class name="com.sun.identity.qatest.authentication.SessionUpgrade"/>
        </classes>
    </test>
    <test name="SessionUpgradeLevelTestSameModule">
        <parameter name="forceAuth" value="false"/>
        <parameter name="testRealm" value="/"/>
        <parameter name="testMode" value="level"/>
        <parameter name="useDifferentModules" value="false"/>
        <parameter name="upgradeTestType" value="extended"/>
        <groups>
            <run>
                <include name="@mode@"/>
            </run>
        </groups>
        <classes>
            <class name="com.sun.identity.qatest.authentication.SessionUpgrade"/>
        </classes>
    </test>
    <test name="SessionUpgradeLevelTestForceAuthSameModule">
        <parameter name="forceAuth" value="true"/>
        <parameter name="testRealm" value="/"/>
        <parameter name="testMode" value="level"/>
        <parameter name="useDifferentModules" value="false"/>
        <parameter name="upgradeTestType" value="extended"/>
        <groups>
            <run>
                <include name="@mode@"/>
            </run>
        </groups>
        <classes>
            <class name="com.sun.identity.qatest.authentication.SessionUpgrade"/>
        </classes>
    </test>
   <test name="SessionUpgradeLevelTestSubRealmSameModule">
        <parameter name="forceAuth" value="false"/>
        <parameter name="testRealm" value="upgradeRealm15"/>
        <parameter name="testMode" value="level"/>
        <parameter name="useDifferentModules" value="false"/>
        <parameter name="upgradeTestType" value="extended"/>
        <groups>
            <run>
                <include name="@mode@"/>
            </run>
        </groups>
        <classes>
            <class name="com.sun.identity.qatest.authentication.SessionUpgrade"/>
        </classes>
    </test>
    <test name="SessionUpgradeLevelTestForceAuthSubRealmSameModule">
        <parameter name="forceAuth" value="true"/>
        <parameter name="testRealm" value="upgradeRealm16"/>
        <parameter name="testMode" value="level"/>
        <parameter name="useDifferentModules" value="false"/>
        <parameter name="upgradeTestType" value="extended"/>
        <groups>
            <run>
                <include name="@mode@"/>
            </run>
        </groups>
        <classes>
            <class name="com.sun.identity.qatest.authentication.SessionUpgrade"/>
        </classes>
    </test>
